{
  "data": {
    "metricsHistory": [
      {
        "id": 26166126,
        "reserveID": "5hVVs474TRejwwfqsecNp97riQGDtSmhTV6jiWSxJfWR",
        "supplyAPY": 4.31961226964879e-7,
        "borrowAPY": 0.000335854695391956,
        "timestamp": 1755181800,
        "supplyAPR": 4.36773344771578e-7,
        "borrowAPR": 0.000335806127581792,
        "cTokenExchangeRate": "0.55165587053690199356"
      },
      {
        "supplyAPY": 4.31961226964879e-7,
        "borrowAPY": 0.000335854695391956,
        "supplyAPR": 4.36773344771578e-7,
        "borrowAPR": 0.000335806127581792,
        "reserveID": "5hVVs474TRejwwfqsecNp97riQGDtSmhTV6jiWSxJfWR",
        "cTokenExchangeRate": "0.55165587053690199356",
        "timestamp": 1755182700
      },
      {
        "supplyAPY": 4.31961226964879e-7,
        "borrowAPY": 0.000335854695391956,
        "supplyAPR": 4.36773344771578e-7,
        "borrowAPR": 0.000335806127581792,
        "reserveID": "5hVVs474TRejwwfqsecNp97riQGDtSmhTV6jiWSxJfWR",
        "cTokenExchangeRate": "0.55165587053690199356",
        "timestamp": 1755183600
      },
      {
        "supplyAPY": 4.31961226964879e-7,
        "borrowAPY": 0.000335854695391956,
        "supplyAPR": 4.36773344771578e-7,
        "borrowAPR": 0.000335806127581792,
        "reserveID": "5hVVs474TRejwwfqsecNp97riQGDtSmhTV6jiWSxJfWR",
        "cTokenExchangeRate": "0.55165587053690199356",
        "timestamp": 1755184500
      },
      {
        "supplyAPY": 4.31961226964879e-7,
        "borrowAPY": 0.000335854695391956,
        "supplyAPR": 4.36773344771578e-7,
        "borrowAPR": 0.000335806127581792,
        "reserveID": "5hVVs474TRejwwfqsecNp97riQGDtSmhTV6jiWSxJfWR",
        "cTokenExchangeRate": "0.55165587053690199356",
        "timestamp": 1755185400
      },
      {
        "supplyAPY": 4.31961226964879e-7,
        "borrowAPY": 0.000335854695391956,
        "supplyAPR": 4.36773344771578e-7,
        "borrowAPR": 0.000335806127581792,
        "reserveID": "5hVVs474TRejwwfqsecNp97riQGDtSmhTV6jiWSxJfWR",
        "cTokenExchangeRate": "0.55165587053690199356",
        "timestamp": 1755186300
      },
      {
        "supplyAPY": 4.31961226964879e-7,
        "borrowAPY": 0.000335854695391956,
        "supplyAPR": 4.36773344771578e-7,
        "borrowAPR": 0.000335806127581792,
        "reserveID": "5hVVs474TRejwwfqsecNp97riQGDtSmhTV6jiWSxJfWR",
        "cTokenExchangeRate": "0.55165587053690199356",
        "timestamp": 1755187200
      },
      {
        "supplyAPY": 4.31961226964879e-7,
        "borrowAPY": 0.000335854695391956,
        "supplyAPR": 4.36773344771578e-7,
        "borrowAPR": 0.000335806127581792,
        "reserveID": "5hVVs474TRejwwfqsecNp97riQGDtSmhTV6jiWSxJfWR",
        "cTokenExchangeRate": "0.55165587053690199356",
        "timestamp": 1755188100
      },
      {
        "supplyAPY": 4.31961226964879e-7,
        "borrowAPY": 0.000335854695391956,
        "supplyAPR": 4.36773344771578e-7,
        "borrowAPR": 0.000335806127581792,
        "reserveID": "5hVVs474TRejwwfqsecNp97riQGDtSmhTV6jiWSxJfWR",
        "cTokenExchangeRate": "0.55165587053690199356",
        "timestamp": 1755189000
      },
      {
        "supplyAPY": 4.31961226964879e-7,
        "borrowAPY": 0.000335854695391956,
        "supplyAPR": 4.36773344771578e-7,
        "borrowAPR": 0.000335806127581792,
        "reserveID": "5hVVs474TRejwwfqsecNp97riQGDtSmhTV6jiWSxJfWR",
        "cTokenExchangeRate": "0.55165587053690199356",
        "timestamp": 1755189900
      },
      {
        "supplyAPY": 4.31961226964879e-7,
        "borrowAPY": 0.000335854695391956,
        "supplyAPR": 4.36773344771578e-7,
        "borrowAPR": 0.000335806127581792,
        "reserveID": "5hVVs474TRejwwfqsecNp97riQGDtSmhTV6jiWSxJfWR",
        "cTokenExchangeRate": "0.55165587053690199356",
        "timestamp": 1755190800
      },
      {
        "supplyAPY": 4.31961226964879e-7,
        "borrowAPY": 0.000335854695391956,
        "supplyAPR": 4.36773344771578e-7,
        "borrowAPR": 0.000335806127581792,
        "reserveID": "5hVVs474TRejwwfqsecNp97riQGDtSmhTV6jiWSxJfWR",
        "cTokenExchangeRate": "0.55165587053690199356",
        "timestamp": 1755191700
      },
      {
        "supplyAPY": 4.31961226964879e-7,
        "borrowAPY": 0.000335854695391956,
        "supplyAPR": 4.36773344771578e-7,
        "borrowAPR": 0.000335806127581792,
        "reserveID": "5hVVs474TRejwwfqsecNp97riQGDtSmhTV6jiWSxJfWR",
        "cTokenExchangeRate": "0.55165587053690199356",
        "timestamp": 1755192600
      },
      {
        "supplyAPY": 4.31961226964879e-7,
        "borrowAPY": 0.000335854695391956,
        "supplyAPR": 4.36773344771578e-7,
        "borrowAPR": 0.000335806127581792,
        "reserveID": "5hVVs474TRejwwfqsecNp97riQGDtSmhTV6jiWSxJfWR",
        "cTokenExchangeRate": "0.55165587053690199356",
        "timestamp": 1755193500
      },
      {
        "supplyAPY": 4.31961226964879e-7,
        "borrowAPY": 0.000335854695391956,
        "supplyAPR": 4.36773344771578e-7,
        "borrowAPR": 0.000335806127581792,
        "reserveID": "5hVVs474TRejwwfqsecNp97riQGDtSmhTV6jiWSxJfWR",
        "cTokenExchangeRate": "0.55165587053690199356",
        "timestamp": 1755194400
      },
      {
        "supplyAPY": 4.31961226964879e-7,
        "borrowAPY": 0.000335854695391956,
        "supplyAPR": 4.36773344771578e-7,
        "borrowAPR": 0.000335806127581792,
        "reserveID": "5hVVs474TRejwwfqsecNp97riQGDtSmhTV6jiWSxJfWR",
        "cTokenExchangeRate": "0.55165587053690199356",
        "timestamp": 1755195300
      },
      {
        "supplyAPY": 4.31961226964879e-7,
        "borrowAPY": 0.000335854695391956,
        "supplyAPR": 4.36773344771578e-7,
        "borrowAPR": 0.000335806127581792,
        "reserveID": "5hVVs474TRejwwfqsecNp97riQGDtSmhTV6jiWSxJfWR",
        "cTokenExchangeRate": "0.55165587053690199356",
        "timestamp": 1755196200
      },
      {
        "supplyAPY": 4.31961226964879e-7,
        "borrowAPY": 0.000335854695391956,
        "supplyAPR": 4.36773344771578e-7,
        "borrowAPR": 0.000335806127581792,
        "reserveID": "5hVVs474TRejwwfqsecNp97riQGDtSmhTV6jiWSxJfWR",
        "cTokenExchangeRate": "0.55165587053690199356",
        "timestamp": 1755197100
      },
      {
        "supplyAPY": 4.31961226964879e-7,
        "borrowAPY": 0.000335854695391956,
        "supplyAPR": 4.36773344771578e-7,
        "borrowAPR": 0.000335806127581792,
        "reserveID": "5hVVs474TRejwwfqsecNp97riQGDtSmhTV6jiWSxJfWR",
        "cTokenExchangeRate": "0.55165587053690199356",
        "timestamp": 1755198000
      },
      {
        "supplyAPY": 4.31961226964879e-7,
        "borrowAPY": 0.000335854695391956,
        "supplyAPR": 4.36773344771578e-7,
        "borrowAPR": 0.000335806127581792,
        "reserveID": "5hVVs474TRejwwfqsecNp97riQGDtSmhTV6jiWSxJfWR",
        "cTokenExchangeRate": "0.55165587053690199356",
        "timestamp": 1755198900
      },
      {
        "supplyAPY": 4.31961226964879e-7,
        "borrowAPY": 0.000335854695391956,
        "supplyAPR": 4.36773344771578e-7,
        "borrowAPR": 0.000335806127581792,
        "reserveID": "5hVVs474TRejwwfqsecNp97riQGDtSmhTV6jiWSxJfWR",
        "cTokenExchangeRate": "0.55165587053690199356",
        "timestamp": 1755199800
      },
      {
        "supplyAPY": 4.31961226964879e-7,
        "borrowAPY": 0.000335854695391956,
        "supplyAPR": 4.36773344771578e-7,
        "borrowAPR": 0.000335806127581792,
        "reserveID": "5hVVs474TRejwwfqsecNp97riQGDtSmhTV6jiWSxJfWR",
        "cTokenExchangeRate": "0.55165587053690199356",
        "timestamp": 1755200700
      },
      {
        "supplyAPY": 4.31961226964879e-7,
        "borrowAPY": 0.000335854695391956,
        "supplyAPR": 4.36773344771578e-7,
        "borrowAPR": 0.000335806127581792,
        "reserveID": "5hVVs474TRejwwfqsecNp97riQGDtSmhTV6jiWSxJfWR",
        "cTokenExchangeRate": "0.55165587053690199356",
        "timestamp": 1755201600
      },
      {
        "supplyAPY": 4.31961226964879e-7,
        "borrowAPY": 0.000335854695391956,
        "supplyAPR": 4.36773344771578e-7,
        "borrowAPR": 0.000335806127581792,
        "reserveID": "5hVVs474TRejwwfqsecNp97riQGDtSmhTV6jiWSxJfWR",
        "cTokenExchangeRate": "0.55165587053690199356",
        "timestamp": 1755202500
      },
      {
        "supplyAPY": 4.31961226964879e-7,
        "borrowAPY": 0.000335854695391956,
        "supplyAPR": 4.36773344771578e-7,
        "borrowAPR": 0.000335806127581792,
        "reserveID": "5hVVs474TRejwwfqsecNp97riQGDtSmhTV6jiWSxJfWR",
        "cTokenExchangeRate": "0.55165587053690199356",
        "timestamp": 1755203400
      },
      {
        "supplyAPY": 4.31961226964879e-7,
        "borrowAPY": 0.000335854695391956,
        "supplyAPR": 4.36773344771578e-7,
        "borrowAPR": 0.000335806127581792,
        "reserveID": "5hVVs474TRejwwfqsecNp97riQGDtSmhTV6jiWSxJfWR",
        "cTokenExchangeRate": "0.55165587053690199356",
        "timestamp": 1755204300
      },
      {
        "supplyAPY": 4.31961226964879e-7,
        "borrowAPY": 0.000335854695391956,
        "supplyAPR": 4.36773344771578e-7,
        "borrowAPR": 0.000335806127581792,
        "reserveID": "5hVVs474TRejwwfqsecNp97riQGDtSmhTV6jiWSxJfWR",
        "cTokenExchangeRate": "0.55165587053690199356",
        "timestamp": 1755205200
      },
      {
        "supplyAPY": 4.31961226964879e-7,
        "borrowAPY": 0.000335854695391956,
        "supplyAPR": 4.36773344771578e-7,
        "borrowAPR": 0.000335806127581792,
        "reserveID": "5hVVs474TRejwwfqsecNp97riQGDtSmhTV6jiWSxJfWR",
        "cTokenExchangeRate": "0.55165587053690199356",
        "timestamp": 1755206100
      },
      {
        "supplyAPY": 4.31961226964879e-7,
        "borrowAPY": 0.000335854695391956,
        "supplyAPR": 4.36773344771578e-7,
        "borrowAPR": 0.000335806127581792,
        "reserveID": "5hVVs474TRejwwfqsecNp97riQGDtSmhTV6jiWSxJfWR",
        "cTokenExchangeRate": "0.55165587053690199356",
        "timestamp": 1755207000
      },
      {
        "supplyAPY": 4.31961226964879e-7,
        "borrowAPY": 0.000335854695391956,
        "supplyAPR": 4.36773344771578e-7,
        "borrowAPR": 0.000335806127581792,
        "reserveID": "5hVVs474TRejwwfqsecNp97riQGDtSmhTV6jiWSxJfWR",
        "cTokenExchangeRate": "0.55165587053690199356",
        "timestamp": 1755207900
      },
      {
        "supplyAPY": 4.31961226964879e-7,
        "borrowAPY": 0.000335854695391956,
        "supplyAPR": 4.36773344771578e-7,
        "borrowAPR": 0.000335806127581792,
        "reserveID": "5hVVs474TRejwwfqsecNp97riQGDtSmhTV6jiWSxJfWR",
        "cTokenExchangeRate": "0.55165587053690199356",
        "timestamp": 1755208800
      },
      {
        "supplyAPY": 4.31961226964879e-7,
        "borrowAPY": 0.000335854695391956,
        "supplyAPR": 4.36773344771578e-7,
        "borrowAPR": 0.000335806127581792,
        "reserveID": "5hVVs474TRejwwfqsecNp97riQGDtSmhTV6jiWSxJfWR",
        "cTokenExchangeRate": "0.55165587053690199356",
        "timestamp": 1755209700
      },
      {
        "supplyAPY": 4.31961226964879e-7,
        "borrowAPY": 0.000335854695391956,
        "supplyAPR": 4.36773344771578e-7,
        "borrowAPR": 0.000335806127581792,
        "reserveID": "5hVVs474TRejwwfqsecNp97riQGDtSmhTV6jiWSxJfWR",
        "cTokenExchangeRate": "0.55165587053690199356",
        "timestamp": 1755210600
      },
      {
        "supplyAPY": 4.31961226964879e-7,
        "borrowAPY": 0.000335854695391956,
        "supplyAPR": 4.36773344771578e-7,
        "borrowAPR": 0.000335806127581792,
        "reserveID": "5hVVs474TRejwwfqsecNp97riQGDtSmhTV6jiWSxJfWR",
        "cTokenExchangeRate": "0.55165587053690199356",
        "timestamp": 1755211500
      },
      {
        "supplyAPY": 4.31961226964879e-7,
        "borrowAPY": 0.000335854695391956,
        "supplyAPR": 4.36773344771578e-7,
        "borrowAPR": 0.000335806127581792,
        "reserveID": "5hVVs474TRejwwfqsecNp97riQGDtSmhTV6jiWSxJfWR",
        "cTokenExchangeRate": "0.55165587053690199356",
        "timestamp": 1755212400
      },
      {
        "supplyAPY": 4.31961226964879e-7,
        "borrowAPY": 0.000335854695391956,
        "supplyAPR": 4.36773344771578e-7,
        "borrowAPR": 0.000335806127581792,
        "reserveID": "5hVVs474TRejwwfqsecNp97riQGDtSmhTV6jiWSxJfWR",
        "cTokenExchangeRate": "0.55165587053690199356",
        "timestamp": 1755213300
      },
      {
        "supplyAPY": 4.31961226964879e-7,
        "borrowAPY": 0.000335854695391956,
        "supplyAPR": 4.36773344771578e-7,
        "borrowAPR": 0.000335806127581792,
        "reserveID": "5hVVs474TRejwwfqsecNp97riQGDtSmhTV6jiWSxJfWR",
        "cTokenExchangeRate": "0.55165587053690199356",
        "timestamp": 1755214200
      },
      {
        "supplyAPY": 4.31961226964879e-7,
        "borrowAPY": 0.000335854695391956,
        "supplyAPR": 4.36773344771578e-7,
        "borrowAPR": 0.000335806127581792,
        "reserveID": "5hVVs474TRejwwfqsecNp97riQGDtSmhTV6jiWSxJfWR",
        "cTokenExchangeRate": "0.55165587053690199356",
        "timestamp": 1755215100
      },
      {
        "supplyAPY": 4.31961226964879e-7,
        "borrowAPY": 0.000335854695391956,
        "supplyAPR": 4.36773344771578e-7,
        "borrowAPR": 0.000335806127581792,
        "reserveID": "5hVVs474TRejwwfqsecNp97riQGDtSmhTV6jiWSxJfWR",
        "cTokenExchangeRate": "0.55165587053690199356",
        "timestamp": 1755216000
      },
      {
        "supplyAPY": 4.31961226964879e-7,
        "borrowAPY": 0.000335854695391956,
        "supplyAPR": 4.36773344771578e-7,
        "borrowAPR": 0.000335806127581792,
        "reserveID": "5hVVs474TRejwwfqsecNp97riQGDtSmhTV6jiWSxJfWR",
        "cTokenExchangeRate": "0.55165587053690199356",
        "timestamp": 1755216900
      },
      {
        "supplyAPY": 4.31961226964879e-7,
        "borrowAPY": 0.000335854695391956,
        "supplyAPR": 4.36773344771578e-7,
        "borrowAPR": 0.000335806127581792,
        "reserveID": "5hVVs474TRejwwfqsecNp97riQGDtSmhTV6jiWSxJfWR",
        "cTokenExchangeRate": "0.55165587053690199356",
        "timestamp": 1755217800
      },
      {
        "supplyAPY": 4.31961226964879e-7,
        "borrowAPY": 0.000335854695391956,
        "supplyAPR": 4.36773344771578e-7,
        "borrowAPR": 0.000335806127581792,
        "reserveID": "5hVVs474TRejwwfqsecNp97riQGDtSmhTV6jiWSxJfWR",
        "cTokenExchangeRate": "0.55165587053690199356",
        "timestamp": 1755218700
      },
      {
        "supplyAPY": 4.31961226964879e-7,
        "borrowAPY": 0.000335854695391956,
        "supplyAPR": 4.36773344771578e-7,
        "borrowAPR": 0.000335806127581792,
        "reserveID": "5hVVs474TRejwwfqsecNp97riQGDtSmhTV6jiWSxJfWR",
        "cTokenExchangeRate": "0.55165587053690199356",
        "timestamp": 1755219600
      },
      {
        "supplyAPY": 4.31961226964879e-7,
        "borrowAPY": 0.000335854695391956,
        "supplyAPR": 4.36773344771578e-7,
        "borrowAPR": 0.000335806127581792,
        "reserveID": "5hVVs474TRejwwfqsecNp97riQGDtSmhTV6jiWSxJfWR",
        "cTokenExchangeRate": "0.55165587053690199356",
        "timestamp": 1755220500
      },
      {
        "supplyAPY": 4.31961226964879e-7,
        "borrowAPY": 0.000335854695391956,
        "supplyAPR": 4.36773344771578e-7,
        "borrowAPR": 0.000335806127581792,
        "reserveID": "5hVVs474TRejwwfqsecNp97riQGDtSmhTV6jiWSxJfWR",
        "cTokenExchangeRate": "0.55165587053690199356",
        "timestamp": 1755221400
      },
      {
        "supplyAPY": 4.31961226964879e-7,
        "borrowAPY": 0.000335854695391956,
        "supplyAPR": 4.36773344771578e-7,
        "borrowAPR": 0.000335806127581792,
        "reserveID": "5hVVs474TRejwwfqsecNp97riQGDtSmhTV6jiWSxJfWR",
        "cTokenExchangeRate": "0.55165587053690199356",
        "timestamp": 1755222300
      },
      {
        "supplyAPY": 4.31961226964879e-7,
        "borrowAPY": 0.000335854695391956,
        "supplyAPR": 4.36773344771578e-7,
        "borrowAPR": 0.000335806127581792,
        "reserveID": "5hVVs474TRejwwfqsecNp97riQGDtSmhTV6jiWSxJfWR",
        "cTokenExchangeRate": "0.55165587053690199356",
        "timestamp": 1755223200
      },
      {
        "supplyAPY": 4.31961226964879e-7,
        "borrowAPY": 0.000335854695391956,
        "supplyAPR": 4.36773344771578e-7,
        "borrowAPR": 0.000335806127581792,
        "reserveID": "5hVVs474TRejwwfqsecNp97riQGDtSmhTV6jiWSxJfWR",
        "cTokenExchangeRate": "0.55165587053690199356",
        "timestamp": 1755224100
      },
      {
        "supplyAPY": 4.31961226964879e-7,
        "borrowAPY": 0.000335854695391956,
        "supplyAPR": 4.36773344771578e-7,
        "borrowAPR": 0.000335806127581792,
        "reserveID": "5hVVs474TRejwwfqsecNp97riQGDtSmhTV6jiWSxJfWR",
        "cTokenExchangeRate": "0.55165587053690199356",
        "timestamp": 1755225000
      },
      {
        "supplyAPY": 4.31961226964879e-7,
        "borrowAPY": 0.000335854695391956,
        "supplyAPR": 4.36773344771578e-7,
        "borrowAPR": 0.000335806127581792,
        "reserveID": "5hVVs474TRejwwfqsecNp97riQGDtSmhTV6jiWSxJfWR",
        "cTokenExchangeRate": "0.55165587053690199356",
        "timestamp": 1755225900
      },
      {
        "supplyAPY": 4.31961226964879e-7,
        "borrowAPY": 0.000335854695391956,
        "supplyAPR": 4.36773344771578e-7,
        "borrowAPR": 0.000335806127581792,
        "reserveID": "5hVVs474TRejwwfqsecNp97riQGDtSmhTV6jiWSxJfWR",
        "cTokenExchangeRate": "0.55165587053690199356",
        "timestamp": 1755226800
      },
      {
        "supplyAPY": 4.31961226964879e-7,
        "borrowAPY": 0.000335854695391956,
        "supplyAPR": 4.36773344771578e-7,
        "borrowAPR": 0.000335806127581792,
        "reserveID": "5hVVs474TRejwwfqsecNp97riQGDtSmhTV6jiWSxJfWR",
        "cTokenExchangeRate": "0.55165587053690199356",
        "timestamp": 1755227700
      },
      {
        "supplyAPY": 4.31961226964879e-7,
        "borrowAPY": 0.000335854695391956,
        "supplyAPR": 4.36773344771578e-7,
        "borrowAPR": 0.000335806127581792,
        "reserveID": "5hVVs474TRejwwfqsecNp97riQGDtSmhTV6jiWSxJfWR",
        "cTokenExchangeRate": "0.55165587053690199356",
        "timestamp": 1755228600
      },
      {
        "supplyAPY": 4.31961226964879e-7,
        "borrowAPY": 0.000335854695391956,
        "supplyAPR": 4.36773344771578e-7,
        "borrowAPR": 0.000335806127581792,
        "reserveID": "5hVVs474TRejwwfqsecNp97riQGDtSmhTV6jiWSxJfWR",
        "cTokenExchangeRate": "0.55165587053690199356",
        "timestamp": 1755229500
      },
      {
        "supplyAPY": 4.31961226964879e-7,
        "borrowAPY": 0.000335854695391956,
        "supplyAPR": 4.36773344771578e-7,
        "borrowAPR": 0.000335806127581792,
        "reserveID": "5hVVs474TRejwwfqsecNp97riQGDtSmhTV6jiWSxJfWR",
        "cTokenExchangeRate": "0.55165587053690199356",
        "timestamp": 1755230400
      },
      {
        "supplyAPY": 4.31961226964879e-7,
        "borrowAPY": 0.000335854695391956,
        "supplyAPR": 4.36773344771578e-7,
        "borrowAPR": 0.000335806127581792,
        "reserveID": "5hVVs474TRejwwfqsecNp97riQGDtSmhTV6jiWSxJfWR",
        "cTokenExchangeRate": "0.55165587053690199356",
        "timestamp": 1755231300
      },
      {
        "supplyAPY": 4.31961226964879e-7,
        "borrowAPY": 0.000335854695391956,
        "supplyAPR": 4.36773344771578e-7,
        "borrowAPR": 0.000335806127581792,
        "reserveID": "5hVVs474TRejwwfqsecNp97riQGDtSmhTV6jiWSxJfWR",
        "cTokenExchangeRate": "0.55165587053690199356",
        "timestamp": 1755232200
      },
      {
        "supplyAPY": 4.31961226964879e-7,
        "borrowAPY": 0.000335854695391956,
        "supplyAPR": 4.36773344771578e-7,
        "borrowAPR": 0.000335806127581792,
        "reserveID": "5hVVs474TRejwwfqsecNp97riQGDtSmhTV6jiWSxJfWR",
        "cTokenExchangeRate": "0.55165587053690199356",
        "timestamp": 1755233100
      },
      {
        "supplyAPY": 4.31961226964879e-7,
        "borrowAPY": 0.000335854695391956,
        "supplyAPR": 4.36773344771578e-7,
        "borrowAPR": 0.000335806127581792,
        "reserveID": "5hVVs474TRejwwfqsecNp97riQGDtSmhTV6jiWSxJfWR",
        "cTokenExchangeRate": "0.55165587053690199356",
        "timestamp": 1755234000
      },
      {
        "supplyAPY": 4.31961226964879e-7,
        "borrowAPY": 0.000335854695391956,
        "supplyAPR": 4.36773344771578e-7,
        "borrowAPR": 0.000335806127581792,
        "reserveID": "5hVVs474TRejwwfqsecNp97riQGDtSmhTV6jiWSxJfWR",
        "cTokenExchangeRate": "0.55165587053690199356",
        "timestamp": 1755234900
      },
      {
        "supplyAPY": 4.31961226964879e-7,
        "borrowAPY": 0.000335854695391956,
        "supplyAPR": 4.36773344771578e-7,
        "borrowAPR": 0.000335806127581792,
        "reserveID": "5hVVs474TRejwwfqsecNp97riQGDtSmhTV6jiWSxJfWR",
        "cTokenExchangeRate": "0.55165587053690199356",
        "timestamp": 1755235800
      },
      {
        "supplyAPY": 4.31961226964879e-7,
        "borrowAPY": 0.000335854695391956,
        "supplyAPR": 4.36773344771578e-7,
        "borrowAPR": 0.000335806127581792,
        "reserveID": "5hVVs474TRejwwfqsecNp97riQGDtSmhTV6jiWSxJfWR",
        "cTokenExchangeRate": "0.55165587053690199356",
        "timestamp": 1755236700
      },
      {
        "supplyAPY": 4.31961226964879e-7,
        "borrowAPY": 0.000335854695391956,
        "supplyAPR": 4.36773344771578e-7,
        "borrowAPR": 0.000335806127581792,
        "reserveID": "5hVVs474TRejwwfqsecNp97riQGDtSmhTV6jiWSxJfWR",
        "cTokenExchangeRate": "0.55165587053690199356",
        "timestamp": 1755237600
      },
      {
        "supplyAPY": 4.31961226964879e-7,
        "borrowAPY": 0.000335854695391956,
        "supplyAPR": 4.36773344771578e-7,
        "borrowAPR": 0.000335806127581792,
        "reserveID": "5hVVs474TRejwwfqsecNp97riQGDtSmhTV6jiWSxJfWR",
        "cTokenExchangeRate": "0.55165587053690199356",
        "timestamp": 1755238500
      },
      {
        "supplyAPY": 4.31961226964879e-7,
        "borrowAPY": 0.000335854695391956,
        "supplyAPR": 4.36773344771578e-7,
        "borrowAPR": 0.000335806127581792,
        "reserveID": "5hVVs474TRejwwfqsecNp97riQGDtSmhTV6jiWSxJfWR",
        "cTokenExchangeRate": "0.55165587053690199356",
        "timestamp": 1755239400
      },
      {
        "supplyAPY": 4.31961226964879e-7,
        "borrowAPY": 0.000335854695391956,
        "supplyAPR": 4.36773344771578e-7,
        "borrowAPR": 0.000335806127581792,
        "reserveID": "5hVVs474TRejwwfqsecNp97riQGDtSmhTV6jiWSxJfWR",
        "cTokenExchangeRate": "0.55165587053690199356",
        "timestamp": 1755240300
      },
      {
        "supplyAPY": 4.31961226964879e-7,
        "borrowAPY": 0.000335854695391956,
        "supplyAPR": 4.36773344771578e-7,
        "borrowAPR": 0.000335806127581792,
        "reserveID": "5hVVs474TRejwwfqsecNp97riQGDtSmhTV6jiWSxJfWR",
        "cTokenExchangeRate": "0.55165587053690199356",
        "timestamp": 1755241200
      },
      {
        "supplyAPY": 4.31961226964879e-7,
        "borrowAPY": 0.000335854695391956,
        "supplyAPR": 4.36773344771578e-7,
        "borrowAPR": 0.000335806127581792,
        "reserveID": "5hVVs474TRejwwfqsecNp97riQGDtSmhTV6jiWSxJfWR",
        "cTokenExchangeRate": "0.55165587053690199356",
        "timestamp": 1755242100
      },
      {
        "supplyAPY": 4.31961226964879e-7,
        "borrowAPY": 0.000335854695391956,
        "supplyAPR": 4.36773344771578e-7,
        "borrowAPR": 0.000335806127581792,
        "reserveID": "5hVVs474TRejwwfqsecNp97riQGDtSmhTV6jiWSxJfWR",
        "cTokenExchangeRate": "0.55165587053690199356",
        "timestamp": 1755243000
      },
      {
        "supplyAPY": 4.31961226964879e-7,
        "borrowAPY": 0.000335854695391956,
        "supplyAPR": 4.36773344771578e-7,
        "borrowAPR": 0.000335806127581792,
        "reserveID": "5hVVs474TRejwwfqsecNp97riQGDtSmhTV6jiWSxJfWR",
        "cTokenExchangeRate": "0.55165587053690199356",
        "timestamp": 1755243900
      },
      {
        "supplyAPY": 4.31961226964879e-7,
        "borrowAPY": 0.000335854695391956,
        "supplyAPR": 4.36773344771578e-7,
        "borrowAPR": 0.000335806127581792,
        "reserveID": "5hVVs474TRejwwfqsecNp97riQGDtSmhTV6jiWSxJfWR",
        "cTokenExchangeRate": "0.55165587053690199356",
        "timestamp": 1755244800
      },
      {
        "supplyAPY": 4.31961226964879e-7,
        "borrowAPY": 0.000335854695391956,
        "supplyAPR": 4.36773344771578e-7,
        "borrowAPR": 0.000335806127581792,
        "reserveID": "5hVVs474TRejwwfqsecNp97riQGDtSmhTV6jiWSxJfWR",
        "cTokenExchangeRate": "0.55165587053690199356",
        "timestamp": 1755245700
      },
      {
        "supplyAPY": 4.31961226964879e-7,
        "borrowAPY": 0.000335854695391956,
        "supplyAPR": 4.36773344771578e-7,
        "borrowAPR": 0.000335806127581792,
        "reserveID": "5hVVs474TRejwwfqsecNp97riQGDtSmhTV6jiWSxJfWR",
        "cTokenExchangeRate": "0.55165587053690199356",
        "timestamp": 1755246600
      },
      {
        "supplyAPY": 4.31961226964879e-7,
        "borrowAPY": 0.000335854695391956,
        "supplyAPR": 4.36773344771578e-7,
        "borrowAPR": 0.000335806127581792,
        "reserveID": "5hVVs474TRejwwfqsecNp97riQGDtSmhTV6jiWSxJfWR",
        "cTokenExchangeRate": "0.55165587053690199356",
        "timestamp": 1755247500
      },
      {
        "supplyAPY": 4.31961226964879e-7,
        "borrowAPY": 0.000335854695391956,
        "supplyAPR": 4.36773344771578e-7,
        "borrowAPR": 0.000335806127581792,
        "reserveID": "5hVVs474TRejwwfqsecNp97riQGDtSmhTV6jiWSxJfWR",
        "cTokenExchangeRate": "0.55165587053690199356",
        "timestamp": 1755248400
      },
      {
        "supplyAPY": 4.31961226964879e-7,
        "borrowAPY": 0.000335854695391956,
        "supplyAPR": 4.36773344771578e-7,
        "borrowAPR": 0.000335806127581792,
        "reserveID": "5hVVs474TRejwwfqsecNp97riQGDtSmhTV6jiWSxJfWR",
        "cTokenExchangeRate": "0.55165587053690199356",
        "timestamp": 1755249300
      },
      {
        "supplyAPY": 4.31961226964879e-7,
        "borrowAPY": 0.000335854695391956,
        "supplyAPR": 4.36773344771578e-7,
        "borrowAPR": 0.000335806127581792,
        "reserveID": "5hVVs474TRejwwfqsecNp97riQGDtSmhTV6jiWSxJfWR",
        "cTokenExchangeRate": "0.55165587053690199356",
        "timestamp": 1755250200
      },
      {
        "supplyAPY": 4.31961226964879e-7,
        "borrowAPY": 0.000335854695391956,
        "supplyAPR": 4.36773344771578e-7,
        "borrowAPR": 0.000335806127581792,
        "reserveID": "5hVVs474TRejwwfqsecNp97riQGDtSmhTV6jiWSxJfWR",
        "cTokenExchangeRate": "0.55165587053690199356",
        "timestamp": 1755251100
      },
      {
        "supplyAPY": 4.31961226964879e-7,
        "borrowAPY": 0.000335854695391956,
        "supplyAPR": 4.36773344771578e-7,
        "borrowAPR": 0.000335806127581792,
        "reserveID": "5hVVs474TRejwwfqsecNp97riQGDtSmhTV6jiWSxJfWR",
        "cTokenExchangeRate": "0.55165587053690199356",
        "timestamp": 1755252000
      },
      {
        "supplyAPY": 4.31961226964879e-7,
        "borrowAPY": 0.000335854695391956,
        "supplyAPR": 4.36773344771578e-7,
        "borrowAPR": 0.000335806127581792,
        "reserveID": "5hVVs474TRejwwfqsecNp97riQGDtSmhTV6jiWSxJfWR",
        "cTokenExchangeRate": "0.55165587053690199356",
        "timestamp": 1755252900
      },
      {
        "supplyAPY": 4.31961226964879e-7,
        "borrowAPY": 0.000335854695391956,
        "supplyAPR": 4.36773344771578e-7,
        "borrowAPR": 0.000335806127581792,
        "reserveID": "5hVVs474TRejwwfqsecNp97riQGDtSmhTV6jiWSxJfWR",
        "cTokenExchangeRate": "0.55165587053690199356",
        "timestamp": 1755253800
      },
      {
        "supplyAPY": 4.31961226964879e-7,
        "borrowAPY": 0.000335854695391956,
        "supplyAPR": 4.36773344771578e-7,
        "borrowAPR": 0.000335806127581792,
        "reserveID": "5hVVs474TRejwwfqsecNp97riQGDtSmhTV6jiWSxJfWR",
        "cTokenExchangeRate": "0.55165587053690199356",
        "timestamp": 1755254700
      },
      {
        "supplyAPY": 4.31961226964879e-7,
        "borrowAPY": 0.000335854695391956,
        "supplyAPR": 4.36773344771578e-7,
        "borrowAPR": 0.000335806127581792,
        "reserveID": "5hVVs474TRejwwfqsecNp97riQGDtSmhTV6jiWSxJfWR",
        "cTokenExchangeRate": "0.55165587053690199356",
        "timestamp": 1755255600
      },
      {
        "supplyAPY": 4.31961226964879e-7,
        "borrowAPY": 0.000335854695391956,
        "supplyAPR": 4.36773344771578e-7,
        "borrowAPR": 0.000335806127581792,
        "reserveID": "5hVVs474TRejwwfqsecNp97riQGDtSmhTV6jiWSxJfWR",
        "cTokenExchangeRate": "0.55165587053690199356",
        "timestamp": 1755256500
      },
      {
        "supplyAPY": 4.31961226964879e-7,
        "borrowAPY": 0.000335854695391956,
        "supplyAPR": 4.36773344771578e-7,
        "borrowAPR": 0.000335806127581792,
        "reserveID": "5hVVs474TRejwwfqsecNp97riQGDtSmhTV6jiWSxJfWR",
        "cTokenExchangeRate": "0.55165587053690199356",
        "timestamp": 1755257400
      },
      {
        "supplyAPY": 4.31961226964879e-7,
        "borrowAPY": 0.000335854695391956,
        "supplyAPR": 4.36773344771578e-7,
        "borrowAPR": 0.000335806127581792,
        "reserveID": "5hVVs474TRejwwfqsecNp97riQGDtSmhTV6jiWSxJfWR",
        "cTokenExchangeRate": "0.55165587053690199356",
        "timestamp": 1755258300
      },
      {
        "supplyAPY": 4.31961226964879e-7,
        "borrowAPY": 0.000335854695391956,
        "supplyAPR": 4.36773344771578e-7,
        "borrowAPR": 0.000335806127581792,
        "reserveID": "5hVVs474TRejwwfqsecNp97riQGDtSmhTV6jiWSxJfWR",
        "cTokenExchangeRate": "0.55165587053690199356",
        "timestamp": 1755259200
      },
      {
        "supplyAPY": 4.31961226964879e-7,
        "borrowAPY": 0.000335854695391956,
        "supplyAPR": 4.36773344771578e-7,
        "borrowAPR": 0.000335806127581792,
        "reserveID": "5hVVs474TRejwwfqsecNp97riQGDtSmhTV6jiWSxJfWR",
        "cTokenExchangeRate": "0.55165587053690199356",
        "timestamp": 1755260100
      },
      {
        "supplyAPY": 4.31961226964879e-7,
        "borrowAPY": 0.000335854695391956,
        "supplyAPR": 4.36773344771578e-7,
        "borrowAPR": 0.000335806127581792,
        "reserveID": "5hVVs474TRejwwfqsecNp97riQGDtSmhTV6jiWSxJfWR",
        "cTokenExchangeRate": "0.55165587053690199356",
        "timestamp": 1755261000
      },
      {
        "supplyAPY": 4.31961226964879e-7,
        "borrowAPY": 0.000335854695391956,
        "supplyAPR": 4.36773344771578e-7,
        "borrowAPR": 0.000335806127581792,
        "reserveID": "5hVVs474TRejwwfqsecNp97riQGDtSmhTV6jiWSxJfWR",
        "cTokenExchangeRate": "0.55165587053690199356",
        "timestamp": 1755261900
      },
      {
        "supplyAPY": 4.31961226964879e-7,
        "borrowAPY": 0.000335854695391956,
        "supplyAPR": 4.36773344771578e-7,
        "borrowAPR": 0.000335806127581792,
        "reserveID": "5hVVs474TRejwwfqsecNp97riQGDtSmhTV6jiWSxJfWR",
        "cTokenExchangeRate": "0.55165587053690199356",
        "timestamp": 1755262800
      },
      {
        "supplyAPY": 4.31961226964879e-7,
        "borrowAPY": 0.000335854695391956,
        "supplyAPR": 4.36773344771578e-7,
        "borrowAPR": 0.000335806127581792,
        "reserveID": "5hVVs474TRejwwfqsecNp97riQGDtSmhTV6jiWSxJfWR",
        "cTokenExchangeRate": "0.55165587053690199356",
        "timestamp": 1755263700
      },
      {
        "supplyAPY": 4.31961226964879e-7,
        "borrowAPY": 0.000335854695391956,
        "supplyAPR": 4.36773344771578e-7,
        "borrowAPR": 0.000335806127581792,
        "reserveID": "5hVVs474TRejwwfqsecNp97riQGDtSmhTV6jiWSxJfWR",
        "cTokenExchangeRate": "0.55165587053690199356",
        "timestamp": 1755264600
      },
      {
        "supplyAPY": 4.31961226964879e-7,
        "borrowAPY": 0.000335854695391956,
        "supplyAPR": 4.36773344771578e-7,
        "borrowAPR": 0.000335806127581792,
        "reserveID": "5hVVs474TRejwwfqsecNp97riQGDtSmhTV6jiWSxJfWR",
        "cTokenExchangeRate": "0.55165587053690199356",
        "timestamp": 1755265500
      },
      {
        "supplyAPY": 4.31961226964879e-7,
        "borrowAPY": 0.000335854695391956,
        "supplyAPR": 4.36773344771578e-7,
        "borrowAPR": 0.000335806127581792,
        "reserveID": "5hVVs474TRejwwfqsecNp97riQGDtSmhTV6jiWSxJfWR",
        "cTokenExchangeRate": "0.55165587053690199356",
        "timestamp": 1755266400
      },
      {
        "id": 26222870,
        "reserveID": "5hVVs474TRejwwfqsecNp97riQGDtSmhTV6jiWSxJfWR",
        "supplyAPY": 4.31961226964879e-7,
        "borrowAPY": 0.000335854695391956,
        "timestamp": 1755267300,
        "supplyAPR": 4.36773344771578e-7,
        "borrowAPR": 0.000335806127581792,
        "cTokenExchangeRate": "0.55165587053690199356"
      }
    ],
    "strategyAnalysis": {
      "apyAnalysis": {
        "confidenceScore": -4275674872.750936,
        "growthDaily": -1.9183743922312105e-13,
        "growthWeekly": -1.3428620745618473e-12,
        "growthMonthly": -5.755123176693632e-12,
        "growthYearly": -7.002066531643918e-11,
        "intercept": 4.3196512416042853e-7
      },
      "aprAnalysis": {
        "confidenceScore": -1396139197.1119792,
        "growthDaily": 1.4031538411748282e-11,
        "growthWeekly": 9.822076888223798e-11,
        "growthMonthly": 4.2094615235244846e-10,
        "growthYearly": 5.1215115202881225e-9,
        "intercept": 0.00033585441033993864
      },
      "cTokenExchangeRateAnalysis": {
        "confidenceScore": -4275675047.2700195,
        "growthDaily": -2.0115613467082337e-7,
        "growthWeekly": -0.0000014080929426957636,
        "growthMonthly": -0.000006034684040124702,
        "growthYearly": -0.00007342198915485053,
        "intercept": 0.5516599570426226
      }
    }
  },
  "timeout": "2025-08-15T14:36:24.338Z"
}